mb_yolo/__init__.py
mb_yolo/dataloader.py
mb_yolo/models.py
mb_yolo/train.py
mb_yolo/utils.py
mb_yolo/version.py
mb_yolo-1.0.22.dist-info/METADATA
mb_yolo-1.0.22.dist-info/WHEEL
mb_yolo-1.0.22.dist-info/top_level.txt
mb_yolo-1.0.22.dist-info/RECORD
