Metadata-Version: 2.2
Name: mb_yolo
Version: 1.0.22
Summary: YOLO function file
Author: ['Malav Bateriwala']
Requires-Python: >=3.8
Requires-Dist: mb_base
Dynamic: author
Dynamic: requires-dist
Dynamic: requires-python
Dynamic: summary
